setup.cfg
setup.py
drf_swagger/__init__.py
drf_swagger/decorator.py
drf_swagger/renderers.py
drf_swagger/views.py
drf_swagger.egg-info/PKG-INFO
drf_swagger.egg-info/SOURCES.txt
drf_swagger.egg-info/dependency_links.txt
drf_swagger.egg-info/requires.txt
drf_swagger.egg-info/top_level.txt
drf_swagger/schema/__init__.py
drf_swagger/schema/drf_serializer.py
drf_swagger/schema/endpoint.py
drf_swagger/schema/schema.py
drf_swagger/schema/settings.py
drf_swagger/schema/utils.py
drf_swagger/schema/view_info.py
drf_swagger/static/favicon-16x16.png
drf_swagger/static/favicon-32x32.png
drf_swagger/static/swagger-ui-bundle.js
drf_swagger/static/swagger-ui-bundle.js.map
drf_swagger/static/swagger-ui-standalone-preset.js
drf_swagger/static/swagger-ui-standalone-preset.js.map
drf_swagger/static/swagger-ui.css
drf_swagger/static/swagger-ui.css.map
drf_swagger/static/swagger-ui.js
drf_swagger/static/swagger-ui.js.map
drf_swagger/templates/index.html
drf_swagger/templates/oauth2-redirect.html
drf_swagger/utils/__init__.py
drf_swagger/utils/data_type.py
drf_swagger/utils/url_path.py